[{"time": 108.091, "outcome": 0}, {"time": 149.096, "outcome": 1}, {"time": 185.355, "outcome": 1}, {"time": 213.004, "outcome": 0}, {"time": 293.784, "outcome": 0}, {"time": 493.434, "outcome": 0}, {"time": 623.021, "outcome": 0}, {"time": 684.313, "outcome": 1}, {"time": 716.189, "outcome": 0}, {"time": 728.794, "outcome": 1}, {"time": 788.646, "outcome": 1}, {"time": 814.796, "outcome": 1}, {"time": 911.782, "outcome": 1}, {"time": 934.13, "outcome": 1}, {"time": 1018.587, "outcome": 0}, {"time": 1106.604, "outcome": 1}, {"time": 1150.693, "outcome": 1}, {"time": 1205.428, "outcome": 1}, {"time": 1244.453, "outcome": 0}, {"time": 1415.278, "outcome": 1}, {"time": 1427.684, "outcome": 1}, {"time": 1446.177, "outcome": 1}]